pvrpm/__init__.py
pvrpm/__main__.py
pvrpm/core/__init__.py
pvrpm/core/case.py
pvrpm/core/components.py
pvrpm/core/enums.py
pvrpm/core/exceptions.py
pvrpm/core/logger.py
pvrpm/core/simulation.py
pvrpm/core/utils.py
pvrpm/core/modules/__init__.py
pvrpm/core/modules/failure.py
pvrpm/core/modules/monitor.py
pvrpm/core/modules/repair.py
pvrpm-1.8.1.dist-info/LICENSE
pvrpm-1.8.1.dist-info/METADATA
pvrpm-1.8.1.dist-info/WHEEL
pvrpm-1.8.1.dist-info/entry_points.txt
pvrpm-1.8.1.dist-info/top_level.txt
pvrpm-1.8.1.dist-info/RECORD
