Metadata-Version: 2.1
Name: pvrpm
Version: 1.8.1
Summary: Run simulations to estimate LCOE costs for PV systems using SAM.
Home-page: https://github.com/FSEC-Photovoltaics/pvrpm-lcoe
Author: ['Brandon Silva', 'Paul Lunis']
Requires-Python: >=3.8
License-File: LICENSE
Requires-Dist: nrel-pysam (==4.0.0)
Requires-Dist: pandas
Requires-Dist: click
Requires-Dist: pyyaml
Requires-Dist: scipy
Requires-Dist: tqdm
Requires-Dist: matplotlib
Requires-Dist: python-dateutil
Provides-Extra: docs
Requires-Dist: sphinx ; extra == 'docs'
Requires-Dist: sphinx-rtd-theme ; extra == 'docs'
Requires-Dist: sphinxcontrib-napoleon ; extra == 'docs'
Provides-Extra: testing
Requires-Dist: pytest ; extra == 'testing'
